Metadata-Version: 2.1
Name: red-py
Version: 0.1.3
Summary: A library of useful tools and extensions
Home-page: https://github.com/zhooda/red-py.git
Author: Zeeshan Hooda
Author-email: zhooda@protonmail.com
License: MIT
Platform: UNKNOWN
Classifier: License :: OSI Approved :: MIT License
Classifier: Intended Audience :: Education
Classifier: Programming Language :: Python :: 3.6
Classifier: Programming Language :: Python :: 3.7
Classifier: Programming Language :: Python :: 3.8
Classifier: Programming Language :: Python :: 3.9
